ablaze/__init__.py
ablaze-0.0.0.dist-info/WHEEL
ablaze-0.0.0.dist-info/METADATA
ablaze-0.0.0.dist-info/RECORD
