Metadata-Version: 2.1
Name: ablaze
Version: 0.0.0
Summary: A Discord library to ease bot development and improve speed of development.
Home-page: https://github.com/vcokltfre/ablaze
License: MIT
Author: vcokltfre
Author-email: vcokltfre@gmail.com
Requires-Python: >=3.8,<4.0
Classifier: License :: OSI Approved :: MIT License
Classifier: Programming Language :: Python :: 3
Classifier: Programming Language :: Python :: 3.8
Classifier: Programming Language :: Python :: 3.9
Project-URL: Repository, https://github.com/vcokltfre/ablaze
